toxo/__init__.py
toxo/cli.py
toxo/core.py
toxo/utils.py
toxo-1.0.9.dist-info/licenses/LICENSE
toxo-1.0.9.dist-info/METADATA
toxo-1.0.9.dist-info/WHEEL
toxo-1.0.9.dist-info/entry_points.txt
toxo-1.0.9.dist-info/top_level.txt
toxo-1.0.9.dist-info/RECORD
