Metadata-Version: 2.4
Name: toxo
Version: 1.0.9
Summary: TOXO Python Library - Smart Layer Platform that converts ANY black-box LLM (GPT, Gemini, Claude) into Context Augmented Language Models (CALM). No LLM retraining needed - just attach .toxo layers for instant domain expertise. Revolutionary AI enhancement technology.
Home-page: https://toxotune.github.io/toxo-docs
Author: ToxoTune
Author-email: ToxoTune <support@toxotune.com>
Maintainer-email: ToxoTune <support@toxotune.com>
License: Proprietary
Project-URL: Homepage, https://toxotune.github.io/toxo-docs
Project-URL: Documentation, https://toxotune.github.io/toxo-docs
Project-URL: Repository, https://github.com/toxotune/toxo-docs
Project-URL: Bug Reports, https://github.com/toxotune/toxo-docs/issues
Keywords: toxo,toxo python library,smart layer,calm,context augmented language models,black-box llm enhancement,llm conversion,domain expert ai,toxo layer,python library,ai augmentation,llm enhancement,no llm retraining,toxo python package,ai layer training,toxo ai,toxo library,ai smart layers,llm memory,ai enhancement
Classifier: Development Status :: 5 - Production/Stable
Classifier: Intended Audience :: Developers
Classifier: Intended Audience :: Science/Research
Classifier: License :: Other/Proprietary License
Classifier: Operating System :: OS Independent
Classifier: Programming Language :: Python :: 3
Classifier: Programming Language :: Python :: 3.8
Classifier: Programming Language :: Python :: 3.9
Classifier: Programming Language :: Python :: 3.10
Classifier: Programming Language :: Python :: 3.11
Classifier: Programming Language :: Python :: 3.12
Classifier: Topic :: Scientific/Engineering :: Artificial Intelligence
Classifier: Topic :: Software Development :: Libraries :: Python Modules
Classifier: Topic :: Communications :: Chat
Classifier: Topic :: Internet :: WWW/HTTP :: Dynamic Content
Classifier: Topic :: Text Processing :: Linguistic
Classifier: Topic :: Education
Classifier: Topic :: Office/Business
Requires-Python: >=3.8
License-File: LICENSE
Requires-Dist: google-generativeai>=0.1.0rc1
Requires-Dist: numpy
Requires-Dist: requests>=2.25.0
Requires-Dist: tqdm>=4.60.0
Requires-Dist: pydantic>=1.8.0
Requires-Dist: typing-extensions>=4.0.0
Provides-Extra: dev
Requires-Dist: pytest>=6.0; extra == "dev"
Requires-Dist: pytest-asyncio>=0.18.0; extra == "dev"
Requires-Dist: black>=21.0.0; extra == "dev"
Requires-Dist: flake8>=3.8.0; extra == "dev"
Requires-Dist: mypy>=0.900; extra == "dev"
Provides-Extra: openai
Requires-Dist: openai>=1.0.0; extra == "openai"
Provides-Extra: claude
Requires-Dist: anthropic>=0.7.0; extra == "claude"
Provides-Extra: full
Requires-Dist: openai>=1.0.0; extra == "full"
Requires-Dist: anthropic>=0.7.0; extra == "full"
Requires-Dist: chromadb>=0.4.0; extra == "full"
Requires-Dist: sentence-transformers>=2.2.0; extra == "full"
Requires-Dist: scikit-learn>=1.0.0; extra == "full"
Requires-Dist: pandas>=1.3.0; extra == "full"
Dynamic: author
Dynamic: home-page
Dynamic: license-file
Dynamic: requires-python
